<annotation>
	<folder>images</folder>
	<filename>DSC_00031.JPG</filename>
	<path>C:\Users\kavin\Desktop\Kolitha\dataset\all\images\DSC_00031.JPG</path>
	<source>
		<database>Unknown</database>
	</source>
	<size>
		<width>1920</width>
		<height>1281</height>
		<depth>3</depth>
	</size>
	<segmented>0</segmented>
	<object>
		<name>knife</name>
		<pose>Unspecified</pose>
		<truncated>0</truncated>
		<difficult>0</difficult>
		<bndbox>
			<xmin>860</xmin>
			<ymin>956</ymin>
			<xmax>932</xmax>
			<ymax>1061</ymax>
		</bndbox>
	</object>
	<object>
		<name>knife in hand</name>
		<pose>Unspecified</pose>
		<truncated>0</truncated>
		<difficult>0</difficult>
		<bndbox>
			<xmin>832</xmin>
			<ymin>875</ymin>
			<xmax>1014</xmax>
			<ymax>1080</ymax>
		</bndbox>
	</object>
	<object>
		<name>person</name>
		<pose>Unspecified</pose>
		<truncated>0</truncated>
		<difficult>0</difficult>
		<bndbox>
			<xmin>981</xmin>
			<ymin>188</ymin>
			<xmax>1443</xmax>
			<ymax>1253</ymax>
		</bndbox>
	</object>
</annotation>
