<annotation>
	<folder>images</folder>
	<filename>knife_590.jpg</filename>
	<path>C:\Users\kavin\Desktop\Kolitha\dataset\all\images\knife_590.jpg</path>
	<source>
		<database>Unknown</database>
	</source>
	<size>
		<width>1300</width>
		<height>863</height>
		<depth>3</depth>
	</size>
	<segmented>0</segmented>
	<object>
		<name>knife</name>
		<pose>Unspecified</pose>
		<truncated>0</truncated>
		<difficult>0</difficult>
		<bndbox>
			<xmin>700</xmin>
			<ymin>279</ymin>
			<xmax>1084</xmax>
			<ymax>616</ymax>
		</bndbox>
	</object>
	<object>
		<name>knife in hand</name>
		<pose>Unspecified</pose>
		<truncated>0</truncated>
		<difficult>0</difficult>
		<bndbox>
			<xmin>23</xmin>
			<ymin>86</ymin>
			<xmax>1123</xmax>
			<ymax>763</ymax>
		</bndbox>
	</object>
</annotation>
