<annotation>
	<folder>images</folder>
	<filename>n03701391_2399.JPEG</filename>
	<path>C:\Users\kavin\Desktop\Kolitha\dataset\all\images\n03701391_2399.JPEG</path>
	<source>
		<database>Unknown</database>
	</source>
	<size>
		<width>349</width>
		<height>231</height>
		<depth>3</depth>
	</size>
	<segmented>0</segmented>
	<object>
		<name>rifle</name>
		<pose>Unspecified</pose>
		<truncated>0</truncated>
		<difficult>0</difficult>
		<bndbox>
			<xmin>8</xmin>
			<ymin>5</ymin>
			<xmax>339</xmax>
			<ymax>227</ymax>
		</bndbox>
	</object>
</annotation>
