<annotation>
	<folder>images</folder>
	<filename>n03701391_11800.JPEG</filename>
	<path>C:\Users\kavin\Desktop\Kolitha\dataset\all\images\n03701391_11800.JPEG</path>
	<source>
		<database>Unknown</database>
	</source>
	<size>
		<width>500</width>
		<height>375</height>
		<depth>3</depth>
	</size>
	<segmented>0</segmented>
	<object>
		<name>rifle</name>
		<pose>Unspecified</pose>
		<truncated>0</truncated>
		<difficult>0</difficult>
		<bndbox>
			<xmin>17</xmin>
			<ymin>99</ymin>
			<xmax>495</xmax>
			<ymax>204</ymax>
		</bndbox>
	</object>
	<object>
		<name>rifle</name>
		<pose>Unspecified</pose>
		<truncated>0</truncated>
		<difficult>0</difficult>
		<bndbox>
			<xmin>22</xmin>
			<ymin>239</ymin>
			<xmax>378</xmax>
			<ymax>350</ymax>
		</bndbox>
	</object>
</annotation>
