<annotation>
	<folder>images</folder>
	<filename>n03701391_15694.JPEG</filename>
	<path>C:\Users\kavin\Desktop\Kolitha\dataset\all\images\n03701391_15694.JPEG</path>
	<source>
		<database>Unknown</database>
	</source>
	<size>
		<width>500</width>
		<height>281</height>
		<depth>3</depth>
	</size>
	<segmented>0</segmented>
	<object>
		<name>rifle</name>
		<pose>Unspecified</pose>
		<truncated>0</truncated>
		<difficult>0</difficult>
		<bndbox>
			<xmin>107</xmin>
			<ymin>32</ymin>
			<xmax>427</xmax>
			<ymax>228</ymax>
		</bndbox>
	</object>
</annotation>
